<?xml version="1.0" encoding="utf-8" standalone="yes"?>
<Gesture Name = "ovalo2Der">
	<Stroke>
		<Point X = "291" Y = "-496" T = "0" Pressure = "255" />
		<Point X = "286" Y = "-496" T = "0" Pressure = "255" />
		<Point X = "284" Y = "-495" T = "0" Pressure = "255" />
		<Point X = "284" Y = "-495" T = "0" Pressure = "255" />
		<Point X = "284" Y = "-495" T = "0" Pressure = "255" />
		<Point X = "284" Y = "-495" T = "0" Pressure = "255" />
		<Point X = "284" Y = "-495" T = "0" Pressure = "255" />
		<Point X = "284" Y = "-495" T = "0" Pressure = "255" />
		<Point X = "284" Y = "-495" T = "0" Pressure = "255" />
		<Point X = "284" Y = "-495" T = "0" Pressure = "255" />
		<Point X = "284" Y = "-495" T = "0" Pressure = "255" />
		<Point X = "284" Y = "-495" T = "0" Pressure = "255" />
		<Point X = "280" Y = "-492" T = "0" Pressure = "255" />
		<Point X = "277" Y = "-490" T = "0" Pressure = "255" />
		<Point X = "272" Y = "-487" T = "0" Pressure = "255" />
		<Point X = "269" Y = "-486" T = "0" Pressure = "255" />
		<Point X = "268" Y = "-485" T = "0" Pressure = "255" />
		<Point X = "268" Y = "-485" T = "0" Pressure = "255" />
		<Point X = "268" Y = "-485" T = "0" Pressure = "255" />
		<Point X = "268" Y = "-485" T = "0" Pressure = "255" />
		<Point X = "265" Y = "-482" T = "0" Pressure = "255" />
		<Point X = "263" Y = "-481" T = "0" Pressure = "255" />
		<Point X = "263" Y = "-481" T = "0" Pressure = "255" />
		<Point X = "260" Y = "-478" T = "0" Pressure = "255" />
		<Point X = "258" Y = "-476" T = "0" Pressure = "255" />
		<Point X = "257" Y = "-475" T = "0" Pressure = "255" />
		<Point X = "254" Y = "-472" T = "0" Pressure = "255" />
		<Point X = "253" Y = "-471" T = "0" Pressure = "255" />
		<Point X = "252" Y = "-468" T = "0" Pressure = "255" />
		<Point X = "250" Y = "-467" T = "0" Pressure = "255" />
		<Point X = "250" Y = "-467" T = "0" Pressure = "255" />
		<Point X = "249" Y = "-465" T = "0" Pressure = "255" />
		<Point X = "248" Y = "-462" T = "0" Pressure = "255" />
		<Point X = "246" Y = "-459" T = "0" Pressure = "255" />
		<Point X = "245" Y = "-457" T = "0" Pressure = "255" />
		<Point X = "244" Y = "-455" T = "0" Pressure = "255" />
		<Point X = "244" Y = "-453" T = "0" Pressure = "255" />
		<Point X = "244" Y = "-453" T = "0" Pressure = "255" />
		<Point X = "242" Y = "-452" T = "0" Pressure = "255" />
		<Point X = "242" Y = "-450" T = "0" Pressure = "255" />
		<Point X = "242" Y = "-447" T = "0" Pressure = "255" />
		<Point X = "242" Y = "-445" T = "0" Pressure = "255" />
		<Point X = "242" Y = "-442" T = "0" Pressure = "255" />
		<Point X = "242" Y = "-442" T = "0" Pressure = "255" />
		<Point X = "242" Y = "-441" T = "0" Pressure = "255" />
		<Point X = "242" Y = "-438" T = "0" Pressure = "255" />
		<Point X = "242" Y = "-437" T = "0" Pressure = "255" />
		<Point X = "242" Y = "-436" T = "0" Pressure = "255" />
		<Point X = "242" Y = "-435" T = "0" Pressure = "255" />
		<Point X = "242" Y = "-433" T = "0" Pressure = "255" />
		<Point X = "242" Y = "-432" T = "0" Pressure = "255" />
		<Point X = "241" Y = "-428" T = "0" Pressure = "255" />
		<Point X = "241" Y = "-425" T = "0" Pressure = "255" />
		<Point X = "241" Y = "-423" T = "0" Pressure = "255" />
		<Point X = "241" Y = "-423" T = "0" Pressure = "255" />
		<Point X = "241" Y = "-420" T = "0" Pressure = "255" />
		<Point X = "241" Y = "-416" T = "0" Pressure = "255" />
		<Point X = "241" Y = "-414" T = "0" Pressure = "255" />
		<Point X = "241" Y = "-412" T = "0" Pressure = "255" />
		<Point X = "241" Y = "-410" T = "0" Pressure = "255" />
		<Point X = "241" Y = "-407" T = "0" Pressure = "255" />
		<Point X = "241" Y = "-407" T = "0" Pressure = "255" />
		<Point X = "241" Y = "-405" T = "0" Pressure = "255" />
		<Point X = "241" Y = "-402" T = "0" Pressure = "255" />
		<Point X = "241" Y = "-399" T = "0" Pressure = "255" />
		<Point X = "241" Y = "-397" T = "0" Pressure = "255" />
		<Point X = "241" Y = "-396" T = "0" Pressure = "255" />
		<Point X = "241" Y = "-393" T = "0" Pressure = "255" />
		<Point X = "241" Y = "-391" T = "0" Pressure = "255" />
		<Point X = "241" Y = "-388" T = "0" Pressure = "255" />
		<Point X = "241" Y = "-385" T = "0" Pressure = "255" />
		<Point X = "241" Y = "-384" T = "0" Pressure = "255" />
		<Point X = "241" Y = "-380" T = "0" Pressure = "255" />
		<Point X = "241" Y = "-379" T = "0" Pressure = "255" />
		<Point X = "241" Y = "-376" T = "0" Pressure = "255" />
		<Point X = "241" Y = "-374" T = "0" Pressure = "255" />
		<Point X = "241" Y = "-371" T = "0" Pressure = "255" />
		<Point X = "241" Y = "-370" T = "0" Pressure = "255" />
		<Point X = "241" Y = "-366" T = "0" Pressure = "255" />
		<Point X = "241" Y = "-363" T = "0" Pressure = "255" />
		<Point X = "241" Y = "-360" T = "0" Pressure = "255" />
		<Point X = "243" Y = "-358" T = "0" Pressure = "255" />
		<Point X = "243" Y = "-357" T = "0" Pressure = "255" />
		<Point X = "243" Y = "-354" T = "0" Pressure = "255" />
		<Point X = "243" Y = "-352" T = "0" Pressure = "255" />
		<Point X = "243" Y = "-347" T = "0" Pressure = "255" />
		<Point X = "243" Y = "-346" T = "0" Pressure = "255" />
		<Point X = "243" Y = "-343" T = "0" Pressure = "255" />
		<Point X = "243" Y = "-342" T = "0" Pressure = "255" />
		<Point X = "244" Y = "-341" T = "0" Pressure = "255" />
		<Point X = "244" Y = "-339" T = "0" Pressure = "255" />
		<Point X = "244" Y = "-336" T = "0" Pressure = "255" />
		<Point X = "245" Y = "-332" T = "0" Pressure = "255" />
		<Point X = "245" Y = "-329" T = "0" Pressure = "255" />
		<Point X = "246" Y = "-327" T = "0" Pressure = "255" />
		<Point X = "246" Y = "-327" T = "0" Pressure = "255" />
		<Point X = "246" Y = "-326" T = "0" Pressure = "255" />
		<Point X = "247" Y = "-325" T = "0" Pressure = "255" />
		<Point X = "248" Y = "-325" T = "0" Pressure = "255" />
		<Point X = "249" Y = "-323" T = "0" Pressure = "255" />
		<Point X = "250" Y = "-323" T = "0" Pressure = "255" />
		<Point X = "250" Y = "-322" T = "0" Pressure = "255" />
		<Point X = "252" Y = "-322" T = "0" Pressure = "255" />
		<Point X = "252" Y = "-322" T = "0" Pressure = "255" />
		<Point X = "253" Y = "-321" T = "0" Pressure = "255" />
		<Point X = "254" Y = "-320" T = "0" Pressure = "255" />
		<Point X = "257" Y = "-318" T = "0" Pressure = "255" />
		<Point X = "257" Y = "-318" T = "0" Pressure = "255" />
		<Point X = "258" Y = "-317" T = "0" Pressure = "255" />
		<Point X = "258" Y = "-317" T = "0" Pressure = "255" />
		<Point X = "260" Y = "-317" T = "0" Pressure = "255" />
		<Point X = "261" Y = "-316" T = "0" Pressure = "255" />
		<Point X = "262" Y = "-315" T = "0" Pressure = "255" />
		<Point X = "262" Y = "-314" T = "0" Pressure = "255" />
		<Point X = "263" Y = "-314" T = "0" Pressure = "255" />
		<Point X = "264" Y = "-314" T = "0" Pressure = "255" />
		<Point X = "267" Y = "-311" T = "0" Pressure = "255" />
		<Point X = "268" Y = "-311" T = "0" Pressure = "255" />
		<Point X = "270" Y = "-310" T = "0" Pressure = "255" />
		<Point X = "270" Y = "-310" T = "0" Pressure = "255" />
		<Point X = "273" Y = "-307" T = "0" Pressure = "255" />
		<Point X = "275" Y = "-306" T = "0" Pressure = "255" />
		<Point X = "277" Y = "-304" T = "0" Pressure = "255" />
		<Point X = "279" Y = "-304" T = "0" Pressure = "255" />
		<Point X = "279" Y = "-304" T = "0" Pressure = "255" />
		<Point X = "280" Y = "-303" T = "0" Pressure = "255" />
		<Point X = "280" Y = "-303" T = "0" Pressure = "255" />
		<Point X = "280" Y = "-303" T = "0" Pressure = "255" />
		<Point X = "281" Y = "-303" T = "0" Pressure = "255" />
		<Point X = "281" Y = "-303" T = "0" Pressure = "255" />
		<Point X = "284" Y = "-302" T = "0" Pressure = "255" />
		<Point X = "284" Y = "-302" T = "0" Pressure = "255" />
		<Point X = "284" Y = "-302" T = "0" Pressure = "255" />
		<Point X = "288" Y = "-302" T = "0" Pressure = "255" />
		<Point X = "289" Y = "-300" T = "0" Pressure = "255" />
		<Point X = "292" Y = "-300" T = "0" Pressure = "255" />
		<Point X = "292" Y = "-300" T = "0" Pressure = "255" />
		<Point X = "292" Y = "-300" T = "0" Pressure = "255" />
		<Point X = "292" Y = "-300" T = "0" Pressure = "255" />
		<Point X = "292" Y = "-300" T = "0" Pressure = "255" />
		<Point X = "293" Y = "-300" T = "0" Pressure = "255" />
		<Point X = "293" Y = "-300" T = "0" Pressure = "255" />
		<Point X = "293" Y = "-300" T = "0" Pressure = "255" />
		<Point X = "293" Y = "-300" T = "0" Pressure = "255" />
		<Point X = "301" Y = "-300" T = "0" Pressure = "255" />
		<Point X = "303" Y = "-300" T = "0" Pressure = "255" />
		<Point X = "304" Y = "-300" T = "0" Pressure = "255" />
		<Point X = "309" Y = "-300" T = "0" Pressure = "255" />
		<Point X = "310" Y = "-300" T = "0" Pressure = "255" />
		<Point X = "310" Y = "-300" T = "0" Pressure = "255" />
		<Point X = "310" Y = "-300" T = "0" Pressure = "255" />
		<Point X = "312" Y = "-300" T = "0" Pressure = "255" />
		<Point X = "313" Y = "-301" T = "0" Pressure = "255" />
		<Point X = "316" Y = "-303" T = "0" Pressure = "255" />
		<Point X = "318" Y = "-304" T = "0" Pressure = "255" />
		<Point X = "319" Y = "-305" T = "0" Pressure = "255" />
		<Point X = "321" Y = "-310" T = "0" Pressure = "255" />
		<Point X = "323" Y = "-313" T = "0" Pressure = "255" />
		<Point X = "325" Y = "-316" T = "0" Pressure = "255" />
		<Point X = "326" Y = "-317" T = "0" Pressure = "255" />
		<Point X = "326" Y = "-318" T = "0" Pressure = "255" />
		<Point X = "326" Y = "-318" T = "0" Pressure = "255" />
		<Point X = "326" Y = "-318" T = "0" Pressure = "255" />
		<Point X = "326" Y = "-324" T = "0" Pressure = "255" />
		<Point X = "326" Y = "-328" T = "0" Pressure = "255" />
		<Point X = "326" Y = "-331" T = "0" Pressure = "255" />
		<Point X = "326" Y = "-334" T = "0" Pressure = "255" />
		<Point X = "326" Y = "-337" T = "0" Pressure = "255" />
		<Point X = "326" Y = "-339" T = "0" Pressure = "255" />
		<Point X = "326" Y = "-341" T = "0" Pressure = "255" />
		<Point X = "326" Y = "-341" T = "0" Pressure = "255" />
		<Point X = "326" Y = "-342" T = "0" Pressure = "255" />
		<Point X = "326" Y = "-344" T = "0" Pressure = "255" />
		<Point X = "326" Y = "-347" T = "0" Pressure = "255" />
		<Point X = "326" Y = "-351" T = "0" Pressure = "255" />
		<Point X = "326" Y = "-354" T = "0" Pressure = "255" />
		<Point X = "326" Y = "-358" T = "0" Pressure = "255" />
		<Point X = "326" Y = "-362" T = "0" Pressure = "255" />
		<Point X = "326" Y = "-363" T = "0" Pressure = "255" />
		<Point X = "326" Y = "-365" T = "0" Pressure = "255" />
		<Point X = "326" Y = "-367" T = "0" Pressure = "255" />
		<Point X = "326" Y = "-373" T = "0" Pressure = "255" />
		<Point X = "326" Y = "-375" T = "0" Pressure = "255" />
		<Point X = "328" Y = "-380" T = "0" Pressure = "255" />
		<Point X = "328" Y = "-382" T = "0" Pressure = "255" />
		<Point X = "329" Y = "-384" T = "0" Pressure = "255" />
		<Point X = "329" Y = "-385" T = "0" Pressure = "255" />
		<Point X = "329" Y = "-388" T = "0" Pressure = "255" />
		<Point X = "329" Y = "-390" T = "0" Pressure = "255" />
		<Point X = "329" Y = "-393" T = "0" Pressure = "255" />
		<Point X = "331" Y = "-397" T = "0" Pressure = "255" />
		<Point X = "331" Y = "-401" T = "0" Pressure = "255" />
		<Point X = "331" Y = "-406" T = "0" Pressure = "255" />
		<Point X = "331" Y = "-408" T = "0" Pressure = "255" />
		<Point X = "331" Y = "-410" T = "0" Pressure = "255" />
		<Point X = "331" Y = "-412" T = "0" Pressure = "255" />
		<Point X = "331" Y = "-415" T = "0" Pressure = "255" />
		<Point X = "331" Y = "-417" T = "0" Pressure = "255" />
		<Point X = "331" Y = "-420" T = "0" Pressure = "255" />
		<Point X = "331" Y = "-424" T = "0" Pressure = "255" />
		<Point X = "331" Y = "-430" T = "0" Pressure = "255" />
		<Point X = "329" Y = "-434" T = "0" Pressure = "255" />
		<Point X = "329" Y = "-436" T = "0" Pressure = "255" />
		<Point X = "328" Y = "-438" T = "0" Pressure = "255" />
		<Point X = "326" Y = "-443" T = "0" Pressure = "255" />
		<Point X = "324" Y = "-447" T = "0" Pressure = "255" />
		<Point X = "323" Y = "-450" T = "0" Pressure = "255" />
		<Point X = "323" Y = "-453" T = "0" Pressure = "255" />
		<Point X = "320" Y = "-457" T = "0" Pressure = "255" />
		<Point X = "318" Y = "-462" T = "0" Pressure = "255" />
		<Point X = "317" Y = "-464" T = "0" Pressure = "255" />
		<Point X = "315" Y = "-467" T = "0" Pressure = "255" />
		<Point X = "315" Y = "-469" T = "0" Pressure = "255" />
		<Point X = "314" Y = "-471" T = "0" Pressure = "255" />
		<Point X = "313" Y = "-474" T = "0" Pressure = "255" />
		<Point X = "311" Y = "-476" T = "0" Pressure = "255" />
		<Point X = "310" Y = "-479" T = "0" Pressure = "255" />
		<Point X = "309" Y = "-482" T = "0" Pressure = "255" />
		<Point X = "308" Y = "-485" T = "0" Pressure = "255" />
		<Point X = "307" Y = "-487" T = "0" Pressure = "255" />
		<Point X = "307" Y = "-487" T = "0" Pressure = "255" />
		<Point X = "306" Y = "-489" T = "0" Pressure = "255" />
		<Point X = "306" Y = "-490" T = "0" Pressure = "255" />
		<Point X = "305" Y = "-490" T = "0" Pressure = "255" />
		<Point X = "304" Y = "-492" T = "0" Pressure = "255" />
		<Point X = "303" Y = "-493" T = "0" Pressure = "255" />
		<Point X = "301" Y = "-494" T = "0" Pressure = "255" />
		<Point X = "301" Y = "-495" T = "0" Pressure = "255" />
		<Point X = "301" Y = "-495" T = "0" Pressure = "255" />
		<Point X = "301" Y = "-495" T = "0" Pressure = "255" />
		<Point X = "301" Y = "-496" T = "0" Pressure = "255" />
		<Point X = "301" Y = "-496" T = "0" Pressure = "255" />
		<Point X = "298" Y = "-496" T = "0" Pressure = "255" />
		<Point X = "297" Y = "-496" T = "0" Pressure = "255" />
		<Point X = "295" Y = "-497" T = "0" Pressure = "255" />
		<Point X = "294" Y = "-497" T = "0" Pressure = "255" />
		<Point X = "294" Y = "-497" T = "0" Pressure = "255" />
		<Point X = "294" Y = "-497" T = "0" Pressure = "255" />
		<Point X = "294" Y = "-497" T = "0" Pressure = "255" />
		<Point X = "294" Y = "-497" T = "0" Pressure = "255" />
		<Point X = "294" Y = "-497" T = "0" Pressure = "255" />
		<Point X = "294" Y = "-497" T = "0" Pressure = "255" />
		<Point X = "294" Y = "-497" T = "0" Pressure = "255" />
		<Point X = "294" Y = "-497" T = "0" Pressure = "255" />
		<Point X = "294" Y = "-497" T = "0" Pressure = "255" />
		<Point X = "294" Y = "-497" T = "0" Pressure = "255" />
		<Point X = "294" Y = "-497" T = "0" Pressure = "255" />
		<Point X = "294" Y = "-497" T = "0" Pressure = "255" />
		<Point X = "294" Y = "-497" T = "0" Pressure = "255" />
		<Point X = "294" Y = "-497" T = "0" Pressure = "255" />
		<Point X = "294" Y = "-497" T = "0" Pressure = "255" />
		<Point X = "291" Y = "-497" T = "0" Pressure = "255" />
		<Point X = "290" Y = "-497" T = "0" Pressure = "255" />
		<Point X = "288" Y = "-497" T = "0" Pressure = "255" />
		<Point X = "288" Y = "-497" T = "0" Pressure = "255" />
		<Point X = "288" Y = "-497" T = "0" Pressure = "255" />
		<Point X = "288" Y = "-496" T = "0" Pressure = "255" />
		<Point X = "288" Y = "-496" T = "0" Pressure = "255" />
		<Point X = "288" Y = "-496" T = "0" Pressure = "255" />
		<Point X = "288" Y = "-496" T = "0" Pressure = "255" />
		<Point X = "288" Y = "-496" T = "0" Pressure = "255" />
		<Point X = "288" Y = "-496" T = "0" Pressure = "255" />
		<Point X = "288" Y = "-496" T = "0" Pressure = "255" />
		<Point X = "288" Y = "-496" T = "0" Pressure = "255" />
		<Point X = "288" Y = "-496" T = "0" Pressure = "255" />
		<Point X = "288" Y = "-496" T = "0" Pressure = "255" />
		<Point X = "288" Y = "-496" T = "0" Pressure = "255" />
		<Point X = "288" Y = "-496" T = "0" Pressure = "255" />
		<Point X = "288" Y = "-496" T = "0" Pressure = "255" />
		<Point X = "288" Y = "-496" T = "0" Pressure = "255" />
		<Point X = "288" Y = "-496" T = "0" Pressure = "255" />
		<Point X = "288" Y = "-496" T = "0" Pressure = "255" />
	</Stroke>
</Gesture>
